spotify_tracks_archiver/__init__.py
spotify_tracks_archiver/__main__.py
spotify_tracks_archiver/api.py
spotify_tracks_archiver/constants.py
spotify_tracks_archiver/main.py
spotify_tracks_archiver/py.typed
spotify_tracks_archiver/version.py
spotify_tracks_archiver-1.0.4.dist-info/LICENSE.md
spotify_tracks_archiver-1.0.4.dist-info/METADATA
spotify_tracks_archiver-1.0.4.dist-info/WHEEL
spotify_tracks_archiver-1.0.4.dist-info/entry_points.txt
spotify_tracks_archiver-1.0.4.dist-info/top_level.txt
spotify_tracks_archiver-1.0.4.dist-info/RECORD
