Metadata-Version: 2.1
Name: spotify-tracks-archiver
Version: 1.0.4
Summary: A python application to back up your "Liked Songs" library from Spotify to a JSON file
License: The MIT License (MIT)
Project-URL: Issues, https://github.com/keller00/spotify-tracks-archiver/issues
Project-URL: Source, https://github.com/keller00/spotify-tracks-archiver
Requires-Python: >=3.9
License-File: LICENSE.md
Requires-Dist: colorama (<1)
Requires-Dist: httpx (<1)
Requires-Dist: python-dotenv (<1)
Provides-Extra: testing
Requires-Dist: pytest ; extra == 'testing'
Requires-Dist: coverage[toml] ; extra == 'testing'
Requires-Dist: covdefaults ; extra == 'testing'
